colortable.py
setup.cfg
setup.py
colortable.egg-info/PKG-INFO
colortable.egg-info/SOURCES.txt
colortable.egg-info/dependency_links.txt
colortable.egg-info/requires.txt
colortable.egg-info/top_level.txt