Metadata-Version: 1.1
Name: colortable
Version: 0.2
Summary: Print colorful(256) tables for terminal with built-in themes
Home-page: https://github.com/lethe3000/ctable
Author: lethe3000
Author-email: lethe30003000@gmail.com
License: UNKNOWN
Download-URL: https://github.com/lethe3000/ctable/tarball/0.1
Keywords: table,terminal,print
Platform: UNKNOWN
